CHANGES.txt
CONTRIBUTORS.txt
MANIFEST.in
README.rst
setup.py
docs/LICENSE.GPL
docs/LICENSE.txt
src/buildout/__init__.py
src/buildout.eggsdirectories.egg-info/PKG-INFO
src/buildout.eggsdirectories.egg-info/SOURCES.txt
src/buildout.eggsdirectories.egg-info/dependency_links.txt
src/buildout.eggsdirectories.egg-info/entry_points.txt
src/buildout.eggsdirectories.egg-info/namespace_packages.txt
src/buildout.eggsdirectories.egg-info/not-zip-safe
src/buildout.eggsdirectories.egg-info/requires.txt
src/buildout.eggsdirectories.egg-info/top_level.txt
src/buildout/eggsdirectories/__init__.py