Metadata-Version: 1.1
Name: buildout.eggsdirectories
Version: 1.0
Summary: zc.buildout extension to include supplementary preloaded egg-directories
Home-page: http://pypi.python.org/pypi/buildout.eggsdirectories
Author: Godefroid Chapelle
Author-email: gotcha@bubblenet.be
License: gpl
Keywords: buildout extension
Platform: UNKNOWN
Classifier: Programming Language :: Python
Classifier: Programming Language :: Python :: 2.6
Classifier: Programming Language :: Python :: 2.7
Classifier: Framework :: Buildout
Classifier: Topic :: Software Development :: Libraries :: Python Modules
